{
    "configurations": [
        {
            "name": "Linux",
            "includePath": [
                "${workspaceFolder}/**",
                "${workspaceFolder}/bazel-workqueue/external/com_google_googletest/googletest/include/",
                "${workspaceFolder}/bazel-workqueue/external/bazel_tools/",
            ],
            "defines": [],
            "compilerPath": "/usr/bin/gcc",
            "cStandard": "c17",
            "cppStandard": "c++20",
            "intelliSenseMode": "linux-gcc-x64"
        }
    ],
    "version": 4
}